IREENLogger.py
IREENLogger-0.0.1.dist-info/METADATA
IREENLogger-0.0.1.dist-info/WHEEL
IREENLogger-0.0.1.dist-info/top_level.txt
IREENLogger-0.0.1.dist-info/RECORD
