Metadata-Version: 2.1
Name: IREENLogger
Version: 0.0.1
Summary: logging package for Ireen
Home-page: https://gitlab.com/ireen-project/scraping/ireen-logger
Author: Mostafa Asadi
Author-email: mostafaasadi73@gmail.com
License: UNKNOWN
Platform: UNKNOWN
Classifier: Programming Language :: Python :: 3
Classifier: License :: OSI Approved :: MIT License
Classifier: Operating System :: OS Independent
Requires-Python: >=3.6
Requires-Dist: redis
